standard_library/__init__.py
standard_library/common_pb2.py
standard_library/common_pb2_grpc.py
standard_library/standardLibraryService_pb2.py
standard_library/standardLibraryService_pb2_grpc.py
standard_library/data_element/__init__.py
standard_library/data_element/interface.py
standard_library/data_element/model.py
standard_library/general/__init__.py
standard_library/general/grpc_client.py
standard_library/general/interface.py
standard_library/general/models.py
standard_library/general/schema.py
longleding_standard_library_service_sdk-0.2.0.dist-info/LICENSE
longleding_standard_library_service_sdk-0.2.0.dist-info/METADATA
longleding_standard_library_service_sdk-0.2.0.dist-info/WHEEL
longleding_standard_library_service_sdk-0.2.0.dist-info/top_level.txt
longleding_standard_library_service_sdk-0.2.0.dist-info/RECORD
